[
  {
    "inputs": [
      {
        "internalType": "address",
        "name": "_owner",
        "type": "address"
      },
      {
        "internalType": "address",
        "name": "_associatedContract",
        "type": "address"
      }
    ],
    "payable": false,
    "stateMutability": "nonpayable",
    "type": "constructor"
  },
  {
    "anonymous": false,
    "inputs": [
      {
        "indexed": false,
        "internalType": "address",
        "name": "associatedContract",
        "type": "address"
      }
    ],
    "name": "AssociatedContractUpdated",
    "type": "event"
  },
  {
    "anonymous": false,
    "inputs": [
      {
        "indexed": false,
        "internalType": "address",
        "name": "oldOwner",
        "type": "address"
      },
      {
        "indexed": false,
        "internalType": "address",
        "name": "newOwner",
        "type": "address"
      }
    ],
    "name": "OwnerChanged",
    "type": "event"
  },
  {
    "anonymous": false,
    "inputs": [
      {
        "indexed": false,
        "internalType": "address",
        "name": "newOwner",
        "type": "address"
      }
    ],
    "name": "OwnerNominated",
    "type": "event"
  },
  {
    "constant": false,
    "inputs": [],
    "name": "acceptOwnership",
    "outputs": [],
    "payable": false,
    "stateMutability": "nonpayable",
    "type": "function"
  },
  {
    "constant": false,
    "inputs": [
      {
        "internalType": "address",
        "name": "account",
        "type": "address"
      },
      {
        "internalType": "bytes32",
        "name": "src",
        "type": "bytes32"
      },
      {
        "internalType": "uint256",
        "name": "amount",
        "type": "uint256"
      },
      {
        "internalType": "bytes32",
        "name": "dest",
        "type": "bytes32"
      },
      {
        "internalType": "uint256",
        "name": "amountReceived",
        "type": "uint256"
      },
      {
        "internalType": "uint256",
        "name": "exchangeFeeRate",
        "type": "uint256"
      },
      {
        "internalType": "uint256",
        "name": "timestamp",
        "type": "uint256"
      },
      {
        "internalType": "uint256",
        "name": "roundIdForSrc",
        "type": "uint256"
      },
      {
        "internalType": "uint256",
        "name": "roundIdForDest",
        "type": "uint256"
      }
    ],
    "name": "appendExchangeEntry",
    "outputs": [],
    "payable": false,
    "stateMutability": "nonpayable",
    "type": "function"
  },
  {
    "constant": true,
    "inputs": [],
    "name": "associatedContract",
    "outputs": [
      {
        "internalType": "address",
        "name": "",
        "type": "address"
      }
    ],
    "payable": false,
    "stateMutability": "view",
    "type": "function"
  },
  {
    "constant": true,
    "inputs": [
      {
        "internalType": "address",
        "name": "",
        "type": "address"
      },
      {
        "internalType": "bytes32",
        "name": "",
        "type": "bytes32"
      },
      {
        "internalType": "uint256",
        "name": "",
        "type": "uint256"
      }
    ],
    "name": "exchanges",
    "outputs": [
      {
        "internalType": "bytes32",
        "name": "src",
        "type": "bytes32"
      },
      {
        "internalType": "uint256",
        "name": "amount",
        "type": "uint256"
      },
      {
        "internalType": "bytes32",
        "name": "dest",
        "type": "bytes32"
      },
      {
        "internalType": "uint256",
        "name": "amountReceived",
        "type": "uint256"
      },
      {
        "internalType": "uint256",
        "name": "exchangeFeeRate",
        "type": "uint256"
      },
      {
        "internalType": "uint256",
        "name": "timestamp",
        "type": "uint256"
      },
      {
        "internalType": "uint256",
        "name": "roundIdForSrc",
        "type": "uint256"
      },
      {
        "internalType": "uint256",
        "name": "roundIdForDest",
        "type": "uint256"
      }
    ],
    "payable": false,
    "stateMutability": "view",
    "type": "function"
  },
  {
    "constant": true,
    "inputs": [
      {
        "internalType": "address",
        "name": "account",
        "type": "address"
      },
      {
        "internalType": "bytes32",
        "name": "currencyKey",
        "type": "bytes32"
      },
      {
        "internalType": "uint256",
        "name": "index",
        "type": "uint256"
      }
    ],
    "name": "getEntryAt",
    "outputs": [
      {
        "internalType": "bytes32",
        "name": "src",
        "type": "bytes32"
      },
      {
        "internalType": "uint256",
        "name": "amount",
        "type": "uint256"
      },
      {
        "internalType": "bytes32",
        "name": "dest",
        "type": "bytes32"
      },
      {
        "internalType": "uint256",
        "name": "amountReceived",
        "type": "uint256"
      },
      {
        "internalType": "uint256",
        "name": "exchangeFeeRate",
        "type": "uint256"
      },
      {
        "internalType": "uint256",
        "name": "timestamp",
        "type": "uint256"
      },
      {
        "internalType": "uint256",
        "name": "roundIdForSrc",
        "type": "uint256"
      },
      {
        "internalType": "uint256",
        "name": "roundIdForDest",
        "type": "uint256"
      }
    ],
    "payable": false,
    "stateMutability": "view",
    "type": "function"
  },
  {
    "constant": true,
    "inputs": [
      {
        "internalType": "address",
        "name": "account",
        "type": "address"
      },
      {
        "internalType": "bytes32",
        "name": "currencyKey",
        "type": "bytes32"
      }
    ],
    "name": "getLengthOfEntries",
    "outputs": [
      {
        "internalType": "uint256",
        "name": "",
        "type": "uint256"
      }
    ],
    "payable": false,
    "stateMutability": "view",
    "type": "function"
  },
  {
    "constant": true,
    "inputs": [
      {
        "internalType": "address",
        "name": "account",
        "type": "address"
      },
      {
        "internalType": "bytes32",
        "name": "currencyKey",
        "type": "bytes32"
      }
    ],
    "name": "getMaxTimestamp",
    "outputs": [
      {
        "internalType": "uint256",
        "name": "",
        "type": "uint256"
      }
    ],
    "payable": false,
    "stateMutability": "view",
    "type": "function"
  },
  {
    "constant": true,
    "inputs": [],
    "name": "maxEntriesInQueue",
    "outputs": [
      {
        "internalType": "uint256",
        "name": "",
        "type": "uint256"
      }
    ],
    "payable": false,
    "stateMutability": "view",
    "type": "function"
  },
  {
    "constant": false,
    "inputs": [
      {
        "internalType": "address",
        "name": "_owner",
        "type": "address"
      }
    ],
    "name": "nominateNewOwner",
    "outputs": [],
    "payable": false,
    "stateMutability": "nonpayable",
    "type": "function"
  },
  {
    "constant": true,
    "inputs": [],
    "name": "nominatedOwner",
    "outputs": [
      {
        "internalType": "address",
        "name": "",
        "type": "address"
      }
    ],
    "payable": false,
    "stateMutability": "view",
    "type": "function"
  },
  {
    "constant": true,
    "inputs": [],
    "name": "owner",
    "outputs": [
      {
        "internalType": "address",
        "name": "",
        "type": "address"
      }
    ],
    "payable": false,
    "stateMutability": "view",
    "type": "function"
  },
  {
    "constant": false,
    "inputs": [
      {
        "internalType": "address",
        "name": "account",
        "type": "address"
      },
      {
        "internalType": "bytes32",
        "name": "currencyKey",
        "type": "bytes32"
      }
    ],
    "name": "removeEntries",
    "outputs": [],
    "payable": false,
    "stateMutability": "nonpayable",
    "type": "function"
  },
  {
    "constant": false,
    "inputs": [
      {
        "internalType": "address",
        "name": "_associatedContract",
        "type": "address"
      }
    ],
    "name": "setAssociatedContract",
    "outputs": [],
    "payable": false,
    "stateMutability": "nonpayable",
    "type": "function"
  },
  {
    "constant": false,
    "inputs": [
      {
        "internalType": "uint256",
        "name": "_maxEntriesInQueue",
        "type": "uint256"
      }
    ],
    "name": "setMaxEntriesInQueue",
    "outputs": [],
    "payable": false,
    "stateMutability": "nonpayable",
    "type": "function"
  }
]
